{
  "journals": [
    {
      "date": "2022-12-07",
      "sleep": "2",
      "journalWriting": "Testing journal",
      "exercise": "60",
      "greenSpace": "60",
      "social": "100",
      "mindful": "5",
      "nutrition": "6",
      "mentalHealth": "90",
      "therapy": "Yes",
      "id": 2
    },
    {
      "date": "2022-12-07",
      "sleep": "1",
      "journalWriting": "ugh",
      "exercise": "1",
      "greenSpace": "3",
      "social": "1",
      "mindful": "1",
      "nutrition": "2",
      "mentalHealth": "1",
      "therapy": "No",
      "id": 3
    },
    {
      "date": "2022-12-07",
      "sleep": "0",
      "journalWriting": "testtttts",
      "exercise": "0",
      "greenSpace": "0",
      "social": "0",
      "mindful": "0",
      "nutrition": "0",
      "mentalHealth": "0",
      "therapy": "",
      "id": 4
    },
    {
      "date": "2022-12-08",
      "sleep": "5",
      "journalWriting": "lala",
      "exercise": "50",
      "greenSpace": "20",
      "social": "5",
      "mindful": "5",
      "nutrition": "7",
      "mentalHealth": "30",
      "therapy": "No",
      "id": 5
    }
  ],
  "comments": [
    {
      "comment": "rfdgdsg",
      "likes": 8,
      "id": 1
    },
    {
      "comment": "vbcvbcb",
      "likes": 3,
      "id": 2
    },
    {
      "comment": "cvbcbcb",
      "likes": 4,
      "id": 3
    }
  ]
}